LICENSE
MANIFEST.in
README.md
setup.py
membersuite_api_client/__init__.py
membersuite_api_client/__init__.pyc
membersuite_api_client/client.py
membersuite_api_client/client.pyc
membersuite_api_client/exceptions.py
membersuite_api_client/exceptions.pyc
membersuite_api_client/mixins.py
membersuite_api_client/mixins.pyc
membersuite_api_client/models.py
membersuite_api_client/models.pyc
membersuite_api_client/utils.py
membersuite_api_client/utils.pyc
membersuite_api_client.egg-info/PKG-INFO
membersuite_api_client.egg-info/SOURCES.txt
membersuite_api_client.egg-info/dependency_links.txt
membersuite_api_client.egg-info/requires.txt
membersuite_api_client.egg-info/top_level.txt
membersuite_api_client/financial/__init__.py
membersuite_api_client/financial/models.py
membersuite_api_client/financial/services.py
membersuite_api_client/memberships/__init__.py
membersuite_api_client/memberships/__init__.pyc
membersuite_api_client/memberships/models.py
membersuite_api_client/memberships/models.pyc
membersuite_api_client/memberships/services.py
membersuite_api_client/memberships/services.pyc
membersuite_api_client/orders/__init__.py
membersuite_api_client/orders/models.py
membersuite_api_client/orders/services.py
membersuite_api_client/organizations/__init__.py
membersuite_api_client/organizations/__init__.pyc
membersuite_api_client/organizations/models.py
membersuite_api_client/organizations/models.pyc
membersuite_api_client/organizations/services.py
membersuite_api_client/security/__init__.py
membersuite_api_client/security/__init__.pyc
membersuite_api_client/security/models.py
membersuite_api_client/security/models.pyc
membersuite_api_client/security/services.py
membersuite_api_client/security/services.pyc
membersuite_api_client/subscriptions/__init__.py
membersuite_api_client/subscriptions/models.py
membersuite_api_client/subscriptions/services.py
membersuite_api_client/tests/README.md
membersuite_api_client/tests/__init__.py
membersuite_api_client/tests/base.py
membersuite_api_client/tests/test_client.py
membersuite_api_client/tests/test_exceptions.py
membersuite_api_client/tests/test_memberships.py
membersuite_api_client/tests/test_organizations.py
membersuite_api_client/tests/test_security.py
