Metadata-Version: 1.1
Name: membersuite-api-client
Version: 1.1.5
Summary: MemberSuite API Client
Home-page: https://github.com/AASHE/python-membersuite-api-client
Author: AASHE
Author-email: webdev@aashe.org
License: UNKNOWN
Platform: UNKNOWN
Classifier: Environment :: Web Environment
Classifier: Intended Audience :: Developers
Classifier: License :: OSI Approved :: BSD License
Classifier: Operating System :: OS Independent
Classifier: Programming Language :: Python :: 3.4
